lumos/__init__.py
lumos/exceptions.py
lumos/py.typed
lumos/shadow.py
lumos_shadowdom-0.2.0.dist-info/licenses/LICENSE
lumos_shadowdom-0.2.0.dist-info/METADATA
lumos_shadowdom-0.2.0.dist-info/WHEEL
lumos_shadowdom-0.2.0.dist-info/top_level.txt
lumos_shadowdom-0.2.0.dist-info/RECORD
