Metadata-Version: 2.4
Name: lumos-shadowdom
Version: 0.2.0
Summary: A robust Shadow DOM traverser for Selenium
Author-email: dhiraj <dhirajdas.666@gmail.com>
License: MIT License
Project-URL: Homepage, https://github.com/godhiraj-code/lumos-shadowdom
Classifier: Programming Language :: Python :: 3
Classifier: License :: OSI Approved :: MIT License
License-File: LICENSE
Requires-Dist: selenium>=3.141.0
Dynamic: license-file
